django_utf8field-1.0.0.dist-info/DESCRIPTION.rst
django_utf8field-1.0.0.dist-info/METADATA
django_utf8field-1.0.0.dist-info/RECORD
django_utf8field-1.0.0.dist-info/WHEEL
django_utf8field-1.0.0.dist-info/metadata.json
django_utf8field-1.0.0.dist-info/top_level.txt
utf8field/__init__.py
utf8field/detector.py
utf8field/fields.py
utf8field/serializer_fields.py
utf8field/validators.py
