Metadata-Version: 2.0
Name: django-utf8field
Version: 1.0.0
Summary: Add UTF-8 Validation to Django FileFields, CharFields and TextFields
Home-page: https://github.com/megasnort/django-utf8field
Author: Stef Bastiaansen
Author-email: stef@megasnort.com
License: Apache
Download-URL: https://github.com/megasnort/django-utf8field/archive/v1.0.0.tar.gz
Keywords: django utf-8
Platform: UNKNOWN
Classifier: Development Status :: 4 - Beta
Classifier: Environment :: Web Environment
Classifier: Programming Language :: Python
Classifier: Intended Audience :: Developers
Classifier: License :: OSI Approved :: Apache Software License
Classifier: Framework :: Django
